setup.py
tornado_pyvows/__init__.py
tornado_pyvows/context.py
tornado_pyvows/version.py
tornado_pyvows.egg-info/PKG-INFO
tornado_pyvows.egg-info/SOURCES.txt
tornado_pyvows.egg-info/dependency_links.txt
tornado_pyvows.egg-info/requires.txt
tornado_pyvows.egg-info/top_level.txt