Metadata-Version: 1.1
Name: tornado-pyvows
Version: 0.5.2
Summary: tornado_pyvows are pyvows extensions to tornado web framework.
Home-page: https://github.com/rafaelcaricio/tornado_pyvows
Author: Rafael Caricio
Author-email: rafael@caricio.com
License: MIT
Keywords: testing vows test tdd
Platform: UNKNOWN
Classifier: Development Status :: 3 - Alpha
Classifier: Intended Audience :: Developers
Classifier: License :: OSI Approved :: MIT License
Classifier: Natural Language :: English
Classifier: Operating System :: MacOS
Classifier: Operating System :: POSIX :: Linux
Classifier: Programming Language :: Python :: 2.6
Classifier: Topic :: Software Development :: Testing
